{
  "count": "1",
  "encounter_type": "Home Visit - Minor Illnesses",
  "entity_id": "",
  "metadata": {
    "start": {
      "openmrs_entity_parent": "",
      "openmrs_entity": "concept",
      "openmrs_data_type": "start",
      "openmrs_entity_id": "163137AAAAAAAAAAAAAAAAAAAAAAAAAAAAAA"
    },
    "end": {
      "openmrs_entity_parent": "",
      "openmrs_entity": "concept",
      "openmrs_data_type": "end",
      "openmrs_entity_id": "163138AAAAAAAAAAAAAAAAAAAAAAAAAAAAAA"
    },
    "today": {
      "openmrs_entity_parent": "",
      "openmrs_entity": "encounter",
      "openmrs_entity_id": "encounter_date"
    },
    "deviceid": {
      "openmrs_entity_parent": "",
      "openmrs_entity": "concept",
      "openmrs_data_type": "deviceid",
      "openmrs_entity_id": "163149AAAAAAAAAAAAAAAAAAAAAAAAAAAAAA"
    },
    "subscriberid": {
      "openmrs_entity_parent": "",
      "openmrs_entity": "concept",
      "openmrs_data_type": "subscriberid",
      "openmrs_entity_id": "163150AAAAAAAAAAAAAAAAAAAAAAAAAAAAAA"
    },
    "simserial": {
      "openmrs_entity_parent": "",
      "openmrs_entity": "concept",
      "openmrs_data_type": "simserial",
      "openmrs_entity_id": "163151AAAAAAAAAAAAAAAAAAAAAAAAAAAAAA"
    },
    "phonenumber": {
      "openmrs_entity_parent": "",
      "openmrs_entity": "concept",
      "openmrs_data_type": "phonenumber",
      "openmrs_entity_id": "163152AAAAAAAAAAAAAAAAAAAAAAAAAAAAAA"
    },
    "encounter_location": ""
  },
  "step1": {
    "title": "ANC Registration",
    "fields": [
      {
        "key": "mild_pain_present",
        "openmrs_entity_parent": "",
        "openmrs_entity": "",
        "openmrs_entity_id": "",
        "type": "check_box",
        "label": "Does the mother have mild pain anywhere in the body?",
        "label_text_style": "normal",
        "text_color": "#C0C0C0",
        "exclusive": [
          "chk_none"
        ],
        "options": [
          {
            "key": "chk_yes",
            "text": "Yes",
            "value": false,
            "openmrs_entity": "",
            "openmrs_entity_id": ""
          },
          {
            "key": "chk_no",
            "text": "No",
            "value": false,
            "openmrs_entity": "",
            "openmrs_entity_id": ""
          }
        ],
        "v_required": {
          "value": "true",
          "err": "Please pick at least one"
        }
      },
      {
        "key": "mild_fever_present",
        "openmrs_entity_parent": "",
        "openmrs_entity": "",
        "openmrs_entity_id": "",
        "type": "check_box",
        "label": "Does the mother have mild fever?",
        "label_text_style": "normal",
        "text_color": "#C0C0C0",
        "exclusive": [
          "chk_none"
        ],
        "options": [
          {
            "key": "chk_yes",
            "text": "Yes",
            "value": false,
            "openmrs_entity": "",
            "openmrs_entity_id": ""
          },
          {
            "key": "chk_no",
            "text": "No",
            "value": false,
            "openmrs_entity": "",
            "openmrs_entity_id": ""
          }
        ],
        "v_required": {
          "value": "true",
          "err": "Please pick at least one"
        }
      },
      {
        "key": "mother_needs_refill",
        "openmrs_entity_parent": "",
        "openmrs_entity": "",
        "openmrs_entity_id": "",
        "type": "check_box",
        "label": "Does the mother need a refill of medicines such as Ferrous Sulphate, folic acid, and SP for IPTp?",
        "label_text_style": "normal",
        "text_color": "#C0C0C0",
        "exclusive": [
          "chk_none"
        ],
        "options": [
          {
            "key": "chk_yes",
            "text": "Yes",
            "value": false,
            "openmrs_entity": "",
            "openmrs_entity_id": ""
          },
          {
            "key": "chk_no",
            "text": "No",
            "value": false,
            "openmrs_entity": "",
            "openmrs_entity_id": ""
          }
        ],
        "v_required": {
          "value": "true",
          "err": "Please pick at least one"
        }
      },
      {
        "key": "mother_needs_refill_other_commodities",
        "openmrs_entity_parent": "",
        "openmrs_entity": "",
        "openmrs_entity_id": "",
        "type": "check_box",
        "label": "Does the mother need a refill of other commodities such as antiseptics/soaps, delivery kit?",
        "label_text_style": "normal",
        "text_color": "#C0C0C0",
        "exclusive": [
          "chk_none"
        ],
        "options": [
          {
            "key": "chk_yes",
            "text": "Yes",
            "value": false,
            "openmrs_entity": "",
            "openmrs_entity_id": ""
          },
          {
            "key": "chk_no",
            "text": "No",
            "value": false,
            "openmrs_entity": "",
            "openmrs_entity_id": ""
          }
        ],
        "v_required": {
          "value": "true",
          "err": "Please pick at least one"
        }
      },
      {
        "key": "minor_illness_present_toaster",
        "openmrs_entity_parent": "",
        "openmrs_entity": "concept",
        "openmrs_entity_id": "",
        "type": "toaster_notes",
        "text": "Recommend that the client visits a nearby ADDO",
        "text_color": "#CF0800",
        "toaster_type": "problem",
        "relevance": {
          "step1:mild_pain_present": {
            "ex-checkbox": [
              {
                "or": [
                  "chk_yes"
                ]
              }
            ]
          }
        }
      },
      {
        "key": "date_of_illness",
        "openmrs_entity_parent": "",
        "openmrs_entity": "concept",
        "openmrs_entity_id": "1730AAAAAAAAAAAAAAAAAAAAAAAAAAAAAAAA",
        "type": "date_picker",
        "hint": "Date ",
        "expanded": false,
        "min_date": "today-1y",
        "max_date": "today",
        "v_required": {
          "value": "true",
          "err": "Please enter the date of illness"
        }
      }
    ]
  }
}